src/__init__.py
src/logic.py
src/main.py
src/test_logic.py
sigmoidpythonpackage-2.0.0.dist-info/METADATA
sigmoidpythonpackage-2.0.0.dist-info/WHEEL
sigmoidpythonpackage-2.0.0.dist-info/top_level.txt
sigmoidpythonpackage-2.0.0.dist-info/RECORD
